LICENSE
README.md
setup.cfg
setup.py
succolib/__init__.py
succolib.egg-info/PKG-INFO
succolib.egg-info/SOURCES.txt
succolib.egg-info/dependency_links.txt
succolib.egg-info/requires.txt
succolib.egg-info/top_level.txt
succolib/io/__init__.py
succolib/io/ascii.py
succolib/io/datasets.py
succolib/io/misc.py
succolib/io/npz.py
succolib/io/root.py
succolib/math_tools/__init__.py
succolib/math_tools/gamma.py
succolib/math_tools/gaussian.py
succolib/math_tools/landau.py
succolib/math_tools/mcs.py
succolib/statistics/__init__.py
succolib/statistics/collections.py
succolib/statistics/profile.py
succolib/statistics/smearing.py
succolib/tracking/__init__.py
succolib/tracking/misc.py
succolib/tracking/straight_2d.py
succolib/visualisation/__init__.py
succolib/visualisation/hist2d_tools.py
succolib/waveforms/__init__.py
succolib/waveforms/wf_analysis_base.py