Metadata-Version: 2.1
Name: succolib
Version: 2024.2.0
Summary: A set of handy, Python-based tools for the INSULAb detectors data analysis
Home-page: https://github.com/mattiasoldani/succolib
Author: Mattia Soldani
Author-email: mattiasoldani93@gmail.com
License: MIT
Download-URL: https://github.com/mattiasoldani/succolib/archive/v2024.2.0.tar.gz
Platform: UNKNOWN
Classifier: Programming Language :: Python
Classifier: License :: OSI Approved :: MIT License
Classifier: Topic :: Scientific/Engineering :: Physics
Classifier: Intended Audience :: Science/Research
Requires-Python: >=3.0
License-File: LICENSE
